{
  "name": "Bundler/InsecureProtocolSource",
  "full_description": "The source `:gemcutter`, `:rubygems` and `:rubyforge` are deprecated because HTTP requests are insecure. Please change your source to 'https://rubygems.org' if possible, or 'http://rubygems.org' if not.",
  "introduction": "No further details provided.",
  "default_enabled": true,
  "style_guide_url": "",
  "is_safe": true,
  "parameters": [
    {
      "parameter_name": "Severity",
      "default_value": "warning",
      "type": "str"
    },
    {
      "parameter_name": "AllowHttpProtocol",
      "default_value": true,
      "type": "bool"
    }
  ]
}