{
  "name": "noGlobalIsNan",
  "group": "suspicious",
  "meta": {
    "description": "",
    "url": "https://biomejs.dev/linter/rules/no-global-is-nan",
    "capabilities": {
      "recommended": true,
      "fixable": true,
      "fix_type": "unsafe",
      "experimental": false
    }
  },
  "content": {
    "introduction": "Belongs to the 'suspicious' group.",
    "options_configuration": {
      "has_options": false,
      "summary": "This rule has no specific options.",
      "schema_code": ""
    }
  }
}