{
    "name": "InefficientEmptyStringCheck",
    "category": "performance",
    "summary": "Checking the length of `string.trim()` or `string.strip()` is an inefficient way\nto decide if a string is really blank, as it creates a new `String` object just to check its size.\nAs of Java 11 you can use `string.isBlank()` to decide if a string consists only of whitespace,\nthat check is equivalent to `string.strip().isEmpty()`. To get the semantic of\n`string.trim().isEmpty()`, you can loop through the characters and compare them to 0x20:\n\n```java\nprivate boolean checkTrimEmpty(String str) {\nreturn str.chars().allMatch(c -> c <= 0x20);\n}\n```\n\nYou can also consider using library functions that include a null check\n(e.g. Apache's `StringUtils#isBlank` in commons-lang,\nSpring's `StringUtils#hasText` in the Spring framework) or use a different definition of whitespace\n(e.g. Google's `CharMatcher#whitespace` in Guava).\n\nCalling `string.strip().isBlank()` is also redundant and should be simplified to `string.isBlank()`.",
    "message": "String.trim().length() == 0 / String.trim().isEmpty() is an inefficient way to validate a blank String.",
    "url": "${pmd.website.baseurl}/pmd_rules_java_performance.html#inefficientemptystringcheck",
    "since": "3.6",
    "priority": "3",
    "is_deprecated": false,
    "configuration": [],
    "examples": "public void bar(String string) {\nif (string != null && string.trim().length() > 0) {\ndoSomething();\n}\n}"
}