{
    "name": "SimplifiedTernary",
    "category": "design",
    "summary": "Reports ternary expression with the form `condition ? literalBoolean : foo`\nor `condition ? foo : literalBoolean`.\n\nThese expressions can be simplified as follows:\n* `condition ? true : expr` simplifies to `condition || expr`\n* `condition ? false : expr` simplifies to `!condition && expr`\n* `condition ? expr : true` simplifies to `!condition || expr`\n* `condition ? expr : false` simplifies to `condition && expr`",
    "message": "This conditional expression can be simplified with || or &&",
    "url": "${pmd.website.baseurl}/pmd_rules_java_design.html#simplifiedternary",
    "since": "5.4.0",
    "priority": "3",
    "is_deprecated": false,
    "configuration": [],
    "examples": "public class Foo {\npublic boolean test() {\nreturn condition ? true : something(); // can be as simple as return condition || something();\n}\n\npublic void test2() {\nfinal boolean value = condition ? false : something(); // can be as simple as value = !condition && something();\n}\n\npublic boolean test3() {\nreturn condition ? something() : true; // can be as simple as return !condition || something();\n}\n\npublic void test4() {\nfinal boolean otherValue = condition ? something() : false; // can be as simple as condition && something();\n}\n\npublic boolean test5() {\nreturn condition ? true : false; // can be as simple as return condition;\n}\n}"
}